[
  {
    "hash": "322c0c1a2ec823d0",
    "word": "demon",
    "pos": "noun",
    "cefr": "C1",
    "decision": "gloss",
    "gloss": "evil spirit",
    "confidence": 0.95
  },
  {
    "hash": "7f2c623c73f2b505",
    "word": "demonstration",
    "pos": "noun",
    "cefr": "B2",
    "decision": "gloss",
    "gloss": "public protest",
    "confidence": 0.94
  },
  {
    "hash": "301b39a352aba276",
    "word": "denote",
    "pos": "verb",
    "cefr": "UNCLASSIFIED",
    "decision": "gloss",
    "gloss": "indicate",
    "confidence": 0.93
  },
  {
    "hash": "314886b1b34fd8d7",
    "word": "denounce",
    "pos": "verb",
    "cefr": "C1",
    "decision": "gloss",
    "gloss": "publicly condemn",
    "confidence": 0.93
  },
  {
    "hash": "7764519ffd28fb4d",
    "word": "dense",
    "pos": "adjective",
    "cefr": "C1",
    "decision": "gloss",
    "gloss": "thickly packed",
    "confidence": 0.93
  },
  {
    "hash": "1f12f8cb29827bed",
    "word": "depart",
    "pos": "verb",
    "cefr": "B2",
    "decision": "gloss",
    "gloss": "leave",
    "confidence": 0.95
  },
  {
    "hash": "afac0ebf65c1c9e3",
    "word": "dependent",
    "pos": "adjective",
    "cefr": "B2",
    "decision": "gloss",
    "gloss": "reliant on; addicted to",
    "confidence": 0.88
  },
  {
    "hash": "f10206c018268529",
    "word": "depict",
    "pos": "verb",
    "cefr": "C1",
    "decision": "gloss",
    "gloss": "show; describe",
    "confidence": 0.9
  },
  {
    "hash": "2f3888f4808372e3",
    "word": "deploy",
    "pos": "verb",
    "cefr": "C1",
    "decision": "gloss",
    "gloss": "position for action",
    "confidence": 0.93
  },
  {
    "hash": "80357c7eb07b788f",
    "word": "deposit",
    "pos": "noun",
    "cefr": "B2",
    "decision": "gloss",
    "gloss": "initial payment; security payment",
    "confidence": 0.88
  },
  {
    "hash": "609547f9479531cf",
    "word": "deposit",
    "pos": "noun",
    "cefr": "C2",
    "decision": "gloss",
    "gloss": "election candidate fee",
    "confidence": 0.92
  },
  {
    "hash": "1913cfa36b614d86",
    "word": "depress",
    "pos": "verb",
    "cefr": "C2",
    "decision": "gloss",
    "gloss": "press down",
    "confidence": 0.95
  },
  {
    "hash": "a92df24ba0a013c9",
    "word": "depress",
    "pos": "verb",
    "cefr": "UNCLASSIFIED",
    "decision": "gloss",
    "gloss": "press down",
    "confidence": 0.95
  },
  {
    "hash": "f1baafd2b2e38040",
    "word": "depression",
    "pos": "noun",
    "cefr": "B2",
    "decision": "gloss",
    "gloss": "clinical sadness",
    "confidence": 0.94
  },
  {
    "hash": "ea7f1603841df17e",
    "word": "deprive",
    "pos": "phrasal verb",
    "cefr": "C1",
    "decision": "gloss",
    "gloss": "prevent from having",
    "confidence": 0.93
  },
  {
    "hash": "b0e8e84b805f3042",
    "word": "deputy",
    "pos": "noun",
    "cefr": "C1",
    "decision": "gloss",
    "gloss": "second-in-command",
    "confidence": 0.94
  },
  {
    "hash": "fba498b2fc719002",
    "word": "derive",
    "pos": "phrasal verb",
    "cefr": "B2",
    "decision": "gloss",
    "gloss": "come from",
    "confidence": 0.95
  },
  {
    "hash": "9593460b17c5157c",
    "word": "descend",
    "pos": "verb",
    "cefr": "C1",
    "decision": "gloss",
    "gloss": "go down",
    "confidence": 0.95
  },
  {
    "hash": "e879ba3835df9cab",
    "word": "descent",
    "pos": "noun",
    "cefr": "C1",
    "decision": "gloss",
    "gloss": "downward movement",
    "confidence": 0.94
  },
  {
    "hash": "4bcf0583bbda7c41",
    "word": "desirable",
    "pos": "adjective",
    "cefr": "C1",
    "decision": "gloss",
    "gloss": "worth wanting",
    "confidence": 0.93
  },
  {
    "hash": "6d82432e58f1ca91",
    "word": "desktop",
    "pos": "noun",
    "cefr": "C1",
    "decision": "gloss",
    "gloss": "computer screen",
    "confidence": 0.95
  },
  {
    "hash": "4dabe309f5073997",
    "word": "destination",
    "pos": "noun",
    "cefr": "B1",
    "decision": "gloss",
    "gloss": "journey endpoint",
    "confidence": 0.93
  },
  {
    "hash": "8ae22b21f29e2e7a",
    "word": "destined",
    "pos": "adjective",
    "cefr": "UNCLASSIFIED",
    "decision": "gloss",
    "gloss": "fated; bound for",
    "confidence": 0.88
  },
  {
    "hash": "685199dff25b6e40",
    "word": "destructive",
    "pos": "adjective",
    "cefr": "C1",
    "decision": "gloss",
    "gloss": "harmful",
    "confidence": 0.93
  },
  {
    "hash": "d3ce1ed96d7ad8ba",
    "word": "detain",
    "pos": "verb",
    "cefr": "C1",
    "decision": "gloss",
    "gloss": "hold officially",
    "confidence": 0.92
  },
  {
    "hash": "d101803567c4685d",
    "word": "deteriorate",
    "pos": "verb",
    "cefr": "C1",
    "decision": "gloss",
    "gloss": "get worse",
    "confidence": 0.95
  },
  {
    "hash": "6fdd958b178aaec3",
    "word": "determination",
    "pos": "noun",
    "cefr": "B2",
    "decision": "gloss",
    "gloss": "perseverance",
    "confidence": 0.95
  },
  {
    "hash": "87ffbc2aebe3ef33",
    "word": "devastate",
    "pos": "verb",
    "cefr": "C1",
    "decision": "gloss",
    "gloss": "destroy; shock deeply",
    "confidence": 0.88
  },
  {
    "hash": "5107583a18b457ac",
    "word": "deviate",
    "pos": "verb",
    "cefr": "UNCLASSIFIED",
    "decision": "gloss",
    "gloss": "stray from",
    "confidence": 0.93
  },
  {
    "hash": "8f863822ba217a93",
    "word": "devil",
    "pos": "noun",
    "cefr": "C1",
    "decision": "gloss",
    "gloss": "evil being",
    "confidence": 0.95
  },
  {
    "hash": "d70044392b84120a",
    "word": "devise",
    "pos": "verb",
    "cefr": "C1",
    "decision": "gloss",
    "gloss": "invent",
    "confidence": 0.95
  },
  {
    "hash": "a13b031ec80a0700",
    "word": "devoid",
    "pos": "adjective",
    "cefr": "UNCLASSIFIED",
    "decision": "gloss",
    "gloss": "completely without",
    "confidence": 0.94
  },
  {
    "hash": "3c4a9ba58dd83295",
    "word": "devote",
    "pos": "phrasal verb",
    "cefr": "B2",
    "decision": "gloss",
    "gloss": "give fully to",
    "confidence": 0.93
  },
  {
    "hash": "2546fc6cabf8e561",
    "word": "devour",
    "pos": "verb",
    "cefr": "C1",
    "decision": "gloss",
    "gloss": "eat quickly",
    "confidence": 0.94
  },
  {
    "hash": "a602c71770256535",
    "word": "devour",
    "pos": "verb",
    "cefr": "UNCLASSIFIED",
    "decision": "gloss",
    "gloss": "eat quickly",
    "confidence": 0.94
  },
  {
    "hash": "52f1301211305d2c",
    "word": "diagnose",
    "pos": "verb",
    "cefr": "C1",
    "decision": "gloss",
    "gloss": "identify the cause",
    "confidence": 0.93
  },
  {
    "hash": "b6ee00d41e60b0b3",
    "word": "dialogue",
    "pos": "noun",
    "cefr": "A1",
    "decision": "gloss",
    "gloss": "conversation",
    "confidence": 0.95
  },
  {
    "hash": "92635386b2feeca4",
    "word": "dictator",
    "pos": "noun",
    "cefr": "C1",
    "decision": "gloss",
    "gloss": "absolute ruler",
    "confidence": 0.94
  },
  {
    "hash": "fb1aea79d51002b7",
    "word": "differ",
    "pos": "verb",
    "cefr": "B2",
    "decision": "gloss",
    "gloss": "be different",
    "confidence": 0.95
  },
  {
    "hash": "54dea4059e9d56ec",
    "word": "dilemma",
    "pos": "noun",
    "cefr": "C1",
    "decision": "gloss",
    "gloss": "difficult choice",
    "confidence": 0.94
  },
  {
    "hash": "2635a4adb70eab7d",
    "word": "diplomat",
    "pos": "noun",
    "cefr": "C1",
    "decision": "gloss",
    "gloss": "government envoy",
    "confidence": 0.94
  },
  {
    "hash": "475963673ab0da68",
    "word": "diplomatic",
    "pos": "adjective",
    "cefr": "C1",
    "decision": "gloss",
    "gloss": "relating to diplomacy; tactful",
    "confidence": 0.88
  },
  {
    "hash": "f1bea2de9bc067a9",
    "word": "directory",
    "pos": "noun",
    "cefr": "C1",
    "decision": "gloss",
    "gloss": "information listing",
    "confidence": 0.93
  },
  {
    "hash": "94de47d8fbcf2226",
    "word": "disability",
    "pos": "noun",
    "cefr": "B2",
    "decision": "gloss",
    "gloss": "physical or mental impairment",
    "confidence": 0.92
  },
  {
    "hash": "5ebab4048c0f6345",
    "word": "disabled",
    "pos": "adjective",
    "cefr": "B2",
    "decision": "gloss",
    "gloss": "having disability",
    "confidence": 0.93
  },
  {
    "hash": "3fd83f9f8b0480f1",
    "word": "disagreement",
    "pos": "noun",
    "cefr": "B2",
    "decision": "gloss",
    "gloss": "difference of opinion",
    "confidence": 0.93
  },
  {
    "hash": "86864e9d1214338d",
    "word": "disappoint",
    "pos": "verb",
    "cefr": "B2",
    "decision": "gloss",
    "gloss": "let down",
    "confidence": 0.94
  },
  {
    "hash": "a1dbdc761b3d071e",
    "word": "disassociate",
    "pos": "verb",
    "cefr": "UNCLASSIFIED",
    "decision": "gloss",
    "gloss": "disconnect from",
    "confidence": 0.93
  },
  {
    "hash": "18e18e2182af03c6",
    "word": "disastrous",
    "pos": "adjective",
    "cefr": "C1",
    "decision": "gloss",
    "gloss": "catastrophic",
    "confidence": 0.94
  },
  {
    "hash": "ce23ad4d1159ae3e",
    "word": "discard",
    "pos": "verb",
    "cefr": "C1",
    "decision": "gloss",
    "gloss": "throw away",
    "confidence": 0.94
  },
  {
    "hash": "525c96a42daf3b50",
    "word": "discipline",
    "pos": "noun",
    "cefr": "B2",
    "decision": "gloss",
    "gloss": "obedience training",
    "confidence": 0.91
  },
  {
    "hash": "dff4dea57900c0b8",
    "word": "disclose",
    "pos": "verb",
    "cefr": "C1",
    "decision": "gloss",
    "gloss": "reveal",
    "confidence": 0.95
  },
  {
    "hash": "22304a8031b370f9",
    "word": "discourage",
    "pos": "verb",
    "cefr": "B2",
    "decision": "gloss",
    "gloss": "dissuade",
    "confidence": 0.93
  },
  {
    "hash": "42baa7038c86de9f",
    "word": "discrete",
    "pos": "adjective",
    "cefr": "UNCLASSIFIED",
    "decision": "gloss",
    "gloss": "separate",
    "confidence": 0.94
  },
  {
    "hash": "cbf5f03a0d44ce10",
    "word": "discriminate",
    "pos": "verb",
    "cefr": "C1",
    "decision": "gloss",
    "gloss": "distinguish",
    "confidence": 0.92
  },
  {
    "hash": "a0e31269175c76d3",
    "word": "discriminate",
    "pos": "verb",
    "cefr": "UNCLASSIFIED",
    "decision": "gloss",
    "gloss": "distinguish",
    "confidence": 0.92
  },
  {
    "hash": "8135198cc4bcc84e",
    "word": "discrimination",
    "pos": "noun",
    "cefr": "C1",
    "decision": "gloss",
    "gloss": "unfair treatment",
    "confidence": 0.93
  },
  {
    "hash": "10cdb4ae67a4e4fa",
    "word": "dismantle",
    "pos": "verb",
    "cefr": "UNCLASSIFIED",
    "decision": "gloss",
    "gloss": "take apart; break up",
    "confidence": 0.88
  },
  {
    "hash": "a0ec6571ff71f00c",
    "word": "disorder",
    "pos": "noun",
    "cefr": "B2",
    "decision": "gloss",
    "gloss": "medical condition",
    "confidence": 0.93
  },
  {
    "hash": "459ecdf2ee985c6d",
    "word": "displace",
    "pos": "verb",
    "cefr": "C1",
    "decision": "gloss",
    "gloss": "force from home",
    "confidence": 0.92
  },
  {
    "hash": "4437a1b52e800c36",
    "word": "dispose",
    "pos": "verb",
    "cefr": "C1",
    "decision": "gloss",
    "gloss": "arrange",
    "confidence": 0.93
  },
  {
    "hash": "c07ddf5974b182a5",
    "word": "disrupt",
    "pos": "verb",
    "cefr": "C1",
    "decision": "gloss",
    "gloss": "disturb",
    "confidence": 0.94
  },
  {
    "hash": "f8eb86fae26c0efd",
    "word": "disruption",
    "pos": "noun",
    "cefr": "C1",
    "decision": "gloss",
    "gloss": "disturbance",
    "confidence": 0.94
  },
  {
    "hash": "4a4f81ce686785fd",
    "word": "dissolve",
    "pos": "verb",
    "cefr": "C1",
    "decision": "gloss",
    "gloss": "mix into liquid",
    "confidence": 0.93
  },
  {
    "hash": "14da50d5b4c338ea",
    "word": "distant",
    "pos": "adjective",
    "cefr": "B2",
    "decision": "gloss",
    "gloss": "far away",
    "confidence": 0.95
  },
  {
    "hash": "f3b02bcd18acbaef",
    "word": "distinctive",
    "pos": "adjective",
    "cefr": "C1",
    "decision": "gloss",
    "gloss": "uniquely recognizable",
    "confidence": 0.92
  },
  {
    "hash": "530729e2bca354e6",
    "word": "distinguish",
    "pos": "verb",
    "cefr": "B2",
    "decision": "gloss",
    "gloss": "tell apart",
    "confidence": 0.93
  },
  {
    "hash": "f15ee65cccb3fa33",
    "word": "distort",
    "pos": "verb",
    "cefr": "C1",
    "decision": "gloss",
    "gloss": "misrepresent",
    "confidence": 0.92
  },
  {
    "hash": "4eaaa9629c60a356",
    "word": "distract",
    "pos": "verb",
    "cefr": "B2",
    "decision": "gloss",
    "gloss": "divert attention",
    "confidence": 0.93
  },
  {
    "hash": "fc248c0d7761c574",
    "word": "disturb",
    "pos": "verb",
    "cefr": "B2",
    "decision": "gloss",
    "gloss": "interrupt",
    "confidence": 0.95
  },
  {
    "hash": "e01242a6e1e52095",
    "word": "disturbing",
    "pos": "adjective",
    "cefr": "C1",
    "decision": "gloss",
    "gloss": "upsetting",
    "confidence": 0.94
  },
  {
    "hash": "180cf4267b986837",
    "word": "diverse",
    "pos": "adjective",
    "cefr": "B2",
    "decision": "gloss",
    "gloss": "varied",
    "confidence": 0.95
  },
  {
    "hash": "5f282d3d4eac38ad",
    "word": "divine",
    "pos": "adjective",
    "cefr": "C1",
    "decision": "gloss",
    "gloss": "of God",
    "confidence": 0.95
  },
  {
    "hash": "05dd03f26e0cbefc",
    "word": "doctrine",
    "pos": "noun",
    "cefr": "C1",
    "decision": "gloss",
    "gloss": "set of beliefs",
    "confidence": 0.93
  },
  {
    "hash": "26fedf9e39702d2f",
    "word": "documentation",
    "pos": "noun",
    "cefr": "C1",
    "decision": "gloss",
    "gloss": "official records",
    "confidence": 0.91
  },
  {
    "hash": "7837a8bd53a5c76f",
    "word": "domesticated",
    "pos": "adjective",
    "cefr": "C1",
    "decision": "gloss",
    "gloss": "tamed",
    "confidence": 0.94
  },
  {
    "hash": "4f67328e5a58d9fc",
    "word": "dominant",
    "pos": "adjective",
    "cefr": "B2",
    "decision": "gloss",
    "gloss": "most important",
    "confidence": 0.93
  },
  {
    "hash": "9437c31fadabda3e",
    "word": "donation",
    "pos": "noun",
    "cefr": "B2",
    "decision": "gloss",
    "gloss": "charitable gift",
    "confidence": 0.92
  },
  {
    "hash": "ca6617444b5e4a40",
    "word": "donor",
    "pos": "noun",
    "cefr": "C1",
    "decision": "gloss",
    "gloss": "giver",
    "confidence": 0.93
  },
  {
    "hash": "3dc77c1af814823a",
    "word": "dose",
    "pos": "noun",
    "cefr": "C1",
    "decision": "gloss",
    "gloss": "measured amount",
    "confidence": 0.92
  },
  {
    "hash": "100df0ea8f098bb2",
    "word": "dot",
    "pos": "noun",
    "cefr": "B2",
    "decision": "gloss",
    "gloss": "small round mark",
    "confidence": 0.94
  },
  {
    "hash": "7dcaad193d1dc74e",
    "word": "drastic",
    "pos": "adjective",
    "cefr": "UNCLASSIFIED",
    "decision": "gloss",
    "gloss": "extreme",
    "confidence": 0.94
  },
  {
    "hash": "3416a482bbadf851",
    "word": "dread",
    "pos": "noun",
    "cefr": "C1",
    "decision": "gloss",
    "gloss": "great fear",
    "confidence": 0.95
  },
  {
    "hash": "f8a62ee549c226ed",
    "word": "dread",
    "pos": "noun",
    "cefr": "UNCLASSIFIED",
    "decision": "gloss",
    "gloss": "great fear",
    "confidence": 0.95
  },
  {
    "hash": "66218aa65f6d2155",
    "word": "driving",
    "pos": "adjective",
    "cefr": "C1",
    "decision": "gloss",
    "gloss": "compelling",
    "confidence": 0.93
  },
  {
    "hash": "fedf3e696f2d61f5",
    "word": "drought",
    "pos": "noun",
    "cefr": "B2",
    "decision": "gloss",
    "gloss": "rain shortage",
    "confidence": 0.95
  },
  {
    "hash": "9961834f300e6a05",
    "word": "drown",
    "pos": "verb",
    "cefr": "C1",
    "decision": "gloss",
    "gloss": "die underwater",
    "confidence": 0.94
  },
  {
    "hash": "cec8ad8af3b0e9df",
    "word": "dual",
    "pos": "adjective",
    "cefr": "C1",
    "decision": "gloss",
    "gloss": "two-part",
    "confidence": 0.95
  },
  {
    "hash": "27c0d5c341fe0b5e",
    "word": "dub",
    "pos": "verb",
    "cefr": "C1",
    "decision": "gloss",
    "gloss": "nickname; re-record audio",
    "confidence": 0.88
  },
  {
    "hash": "d6cbbf4870efac8a",
    "word": "dull",
    "pos": "adjective",
    "cefr": "B2",
    "decision": "gloss",
    "gloss": "boring",
    "confidence": 0.95
  },
  {
    "hash": "2a37449dcc3acb7e",
    "word": "dumb",
    "pos": "adjective",
    "cefr": "C1",
    "decision": "gloss",
    "gloss": "stupid; silent",
    "confidence": 0.88
  },
  {
    "hash": "3875adc4ada6cc84",
    "word": "dump",
    "pos": "verb",
    "cefr": "B2",
    "decision": "gloss",
    "gloss": "discard",
    "confidence": 0.94
  },
  {
    "hash": "cf1b8b4401cbf445",
    "word": "duo",
    "pos": "noun",
    "cefr": "C1",
    "decision": "gloss",
    "gloss": "pair",
    "confidence": 0.95
  },
  {
    "hash": "2b6504eee01c6a82",
    "word": "durable",
    "pos": "adjective",
    "cefr": "UNCLASSIFIED",
    "decision": "gloss",
    "gloss": "long-lasting",
    "confidence": 0.95
  },
  {
    "hash": "930b81aac5a052e1",
    "word": "duration",
    "pos": "noun",
    "cefr": "B2",
    "decision": "gloss",
    "gloss": "time length",
    "confidence": 0.93
  },
  {
    "hash": "dadd2425f6b76866",
    "word": "dynamic",
    "pos": "adjective",
    "cefr": "B2",
    "decision": "gloss",
    "gloss": "energetic",
    "confidence": 0.94
  },
  {
    "hash": "6c3aaad663c1274a",
    "word": "dysfunctional",
    "pos": "adjective",
    "cefr": "UNCLASSIFIED",
    "decision": "gloss",
    "gloss": "malfunctioning",
    "confidence": 0.93
  },
  {
    "hash": "bfa0fd989a38e3b0",
    "word": "eager",
    "pos": "adjective",
    "cefr": "C1",
    "decision": "gloss",
    "gloss": "keen",
    "confidence": 0.94
  },
  {
    "hash": "62de79939a24eb52",
    "word": "earnings",
    "pos": "noun",
    "cefr": "C1",
    "decision": "gloss",
    "gloss": "income",
    "confidence": 0.93
  },
  {
    "hash": "54587318ad7271d7",
    "word": "eccentric",
    "pos": "adjective",
    "cefr": "UNCLASSIFIED",
    "decision": "gloss",
    "gloss": "unconventional",
    "confidence": 0.94
  },
  {
    "hash": "d8659b96d618e7c3",
    "word": "ecological",
    "pos": "adjective",
    "cefr": "C1",
    "decision": "gloss",
    "gloss": "environmental",
    "confidence": 0.92
  },
  {
    "hash": "569f32cc79bd302d",
    "word": "economics",
    "pos": "noun",
    "cefr": "B2",
    "decision": "gloss",
    "gloss": "study of money systems",
    "confidence": 0.93
  },
  {
    "hash": "6ede4ea36d0b5161",
    "word": "economist",
    "pos": "noun",
    "cefr": "B2",
    "decision": "gloss",
    "gloss": "money-systems expert",
    "confidence": 0.92
  },
  {
    "hash": "693729ae95ce18c9",
    "word": "editorial",
    "pos": "adjective",
    "cefr": "B2",
    "decision": "gloss",
    "gloss": "publication-related",
    "confidence": 0.92
  },
  {
    "hash": "bf0143521609490d",
    "word": "educator",
    "pos": "noun",
    "cefr": "C1",
    "decision": "gloss",
    "gloss": "teacher",
    "confidence": 0.95
  },
  {
    "hash": "fb198895f7746557",
    "word": "efficient",
    "pos": "adjective",
    "cefr": "B2",
    "decision": "gloss",
    "gloss": "productive",
    "confidence": 0.93
  },
  {
    "hash": "e9ff1e3d59ba6eaf",
    "word": "efficiently",
    "pos": "adverb",
    "cefr": "B2",
    "decision": "gloss",
    "gloss": "productively",
    "confidence": 0.93
  },
  {
    "hash": "e0df3ee52eaa6f2c",
    "word": "effortless",
    "pos": "adjective",
    "cefr": "UNCLASSIFIED",
    "decision": "gloss",
    "gloss": "easy",
    "confidence": 0.95
  },
  {
    "hash": "bfc3a8b04a9bfdb5",
    "word": "ego",
    "pos": "noun",
    "cefr": "C1",
    "decision": "gloss",
    "gloss": "self-importance",
    "confidence": 0.94
  },
  {
    "hash": "5652fbec74dacbe9",
    "word": "elaborate",
    "pos": "adjective",
    "cefr": "C1",
    "decision": "gloss",
    "gloss": "complex, detailed",
    "confidence": 0.91
  },
  {
    "hash": "3745aeefb4941c76",
    "word": "elasticity",
    "pos": "noun",
    "cefr": "UNCLASSIFIED",
    "decision": "gloss",
    "gloss": "stretchiness",
    "confidence": 0.93
  },
  {
    "hash": "4ab8250d113acae9",
    "word": "elbow",
    "pos": "noun",
    "cefr": "B2",
    "decision": "gloss",
    "gloss": "arm joint",
    "confidence": 0.95
  },
  {
    "hash": "5d43a316991becbb",
    "word": "electoral",
    "pos": "adjective",
    "cefr": "C1",
    "decision": "gloss",
    "gloss": "election-related",
    "confidence": 0.94
  },
  {
    "hash": "53d633b1089d34c9",
    "word": "elegant",
    "pos": "adjective",
    "cefr": "B2",
    "decision": "gloss",
    "gloss": "stylish",
    "confidence": 0.93
  },
  {
    "hash": "53849ffed25599b1",
    "word": "elementary",
    "pos": "adjective",
    "cefr": "B2",
    "decision": "gloss",
    "gloss": "basic",
    "confidence": 0.95
  },
  {
    "hash": "8f7102e38a53fe7a",
    "word": "elevate",
    "pos": "verb",
    "cefr": "C1",
    "decision": "gloss",
    "gloss": "raise up",
    "confidence": 0.93
  },
  {
    "hash": "de85b42a5efe2e97",
    "word": "eligible",
    "pos": "adjective",
    "cefr": "C1",
    "decision": "gloss",
    "gloss": "qualified",
    "confidence": 0.93
  },
  {
    "hash": "617cc6dd63928840",
    "word": "eliminate",
    "pos": "verb",
    "cefr": "B2",
    "decision": "gloss",
    "gloss": "remove",
    "confidence": 0.95
  },
  {
    "hash": "cfc0265e8de84651",
    "word": "elite",
    "pos": "noun",
    "cefr": "C1",
    "decision": "gloss",
    "gloss": "powerful minority",
    "confidence": 0.93
  },
  {
    "hash": "5b6aa77266652c8f",
    "word": "embark",
    "pos": "verb",
    "cefr": "C1",
    "decision": "gloss",
    "gloss": "board a vessel",
    "confidence": 0.93
  },
  {
    "hash": "a8ba18bdc1577720",
    "word": "embassy",
    "pos": "noun",
    "cefr": "C1",
    "decision": "gloss",
    "gloss": "diplomatic office",
    "confidence": 0.93
  },
  {
    "hash": "b921a1933da194b2",
    "word": "embed",
    "pos": "verb",
    "cefr": "C1",
    "decision": "gloss",
    "gloss": "fix firmly",
    "confidence": 0.94
  },
  {
    "hash": "b936247b1c0e988b",
    "word": "embody",
    "pos": "verb",
    "cefr": "C1",
    "decision": "gloss",
    "gloss": "represent",
    "confidence": 0.94
  },
  {
    "hash": "e6bb67dc12fccdba",
    "word": "embossed",
    "pos": "adjective",
    "cefr": "UNCLASSIFIED",
    "decision": "gloss",
    "gloss": "raised-pattern",
    "confidence": 0.93
  },
  {
    "hash": "6a94a1ee93455cfd",
    "word": "embrace",
    "pos": "verb",
    "cefr": "B2",
    "decision": "gloss",
    "gloss": "hug; adopt",
    "confidence": 0.88
  },
  {
    "hash": "64aeabbbd1e6bf33",
    "word": "embryo",
    "pos": "noun",
    "cefr": "C1",
    "decision": "gloss",
    "gloss": "early-stage organism",
    "confidence": 0.92
  },
  {
    "hash": "2cab9aa793a2bc07",
    "word": "embryo",
    "pos": "noun",
    "cefr": "UNCLASSIFIED",
    "decision": "gloss",
    "gloss": "early-stage organism",
    "confidence": 0.92
  },
  {
    "hash": "5d3a82a97bfddbc3",
    "word": "emission",
    "pos": "noun",
    "cefr": "B2",
    "decision": "gloss",
    "gloss": "released substance",
    "confidence": 0.91
  },
  {
    "hash": "fe8dc656c6116239",
    "word": "emotionally",
    "pos": "adverb",
    "cefr": "B2",
    "decision": "gloss",
    "gloss": "with feeling",
    "confidence": 0.93
  },
  {
    "hash": "7c720ef75d51ed9c",
    "word": "empire",
    "pos": "noun",
    "cefr": "B2",
    "decision": "gloss",
    "gloss": "ruled territory group",
    "confidence": 0.92
  },
  {
    "hash": "0fb83a293f7b1148",
    "word": "empirical",
    "pos": "adjective",
    "cefr": "C1",
    "decision": "gloss",
    "gloss": "experience-based",
    "confidence": 0.93
  },
  {
    "hash": "d435db2198f12c10",
    "word": "empower",
    "pos": "verb",
    "cefr": "C1",
    "decision": "gloss",
    "gloss": "authorize",
    "confidence": 0.92
  },
  {
    "hash": "188b1bfd0a13fdba",
    "word": "enact",
    "pos": "verb",
    "cefr": "C1",
    "decision": "gloss",
    "gloss": "make law",
    "confidence": 0.95
  },
  {
    "hash": "6147b074205e78af",
    "word": "encompass",
    "pos": "verb",
    "cefr": "C1",
    "decision": "gloss",
    "gloss": "include",
    "confidence": 0.95
  },
  {
    "hash": "f6eb665a137b3abc",
    "word": "encouraging",
    "pos": "adjective",
    "cefr": "C1",
    "decision": "gloss",
    "gloss": "supportive",
    "confidence": 0.93
  },
  {
    "hash": "ab2bfb684201ebda",
    "word": "endeavour",
    "pos": "noun",
    "cefr": "C1",
    "decision": "gloss",
    "gloss": "difficult attempt",
    "confidence": 0.92
  },
  {
    "hash": "d1c4ca844e081ab1",
    "word": "endless",
    "pos": "adjective",
    "cefr": "C1",
    "decision": "gloss",
    "gloss": "never-ending",
    "confidence": 0.93
  },
  {
    "hash": "cae89c38667c82eb",
    "word": "endorse",
    "pos": "verb",
    "cefr": "C1",
    "decision": "gloss",
    "gloss": "publicly support",
    "confidence": 0.92
  },
  {
    "hash": "6e3ae8eb638b46e8",
    "word": "endorsement",
    "pos": "noun",
    "cefr": "C1",
    "decision": "gloss",
    "gloss": "public support",
    "confidence": 0.92
  },
  {
    "hash": "b286787eecb0e3a9",
    "word": "endure",
    "pos": "verb",
    "cefr": "C1",
    "decision": "gloss",
    "gloss": "suffer through",
    "confidence": 0.93
  },
  {
    "hash": "795c048c295a46b2",
    "word": "enforce",
    "pos": "verb",
    "cefr": "C1",
    "decision": "gloss",
    "gloss": "compel obedience",
    "confidence": 0.92
  },
  {
    "hash": "f0095b1fc3bef733",
    "word": "engage",
    "pos": "verb",
    "cefr": "B2",
    "decision": "gloss",
    "gloss": "capture attention; employ",
    "confidence": 0.88
  },
  {
    "hash": "9141558bb391bd37",
    "word": "engaged",
    "pos": "adjective",
    "cefr": "B1",
    "decision": "gloss",
    "gloss": "promised to marry",
    "confidence": 0.95
  },
  {
    "hash": "39838d2d29b5e0e8",
    "word": "engaging",
    "pos": "adjective",
    "cefr": "C1",
    "decision": "gloss",
    "gloss": "captivating",
    "confidence": 0.94
  },
  {
    "hash": "7151e2c0021e7dc6",
    "word": "enjoyable",
    "pos": "adjective",
    "cefr": "B2",
    "decision": "gloss",
    "gloss": "pleasant",
    "confidence": 0.95
  },
  {
    "hash": "40c2a2a4287d47a5",
    "word": "enquire",
    "pos": "verb",
    "cefr": "C1",
    "decision": "gloss",
    "gloss": "ask",
    "confidence": 0.95
  },
  {
    "hash": "a05d1024b04cf1e2",
    "word": "enrich",
    "pos": "verb",
    "cefr": "C1",
    "decision": "gloss",
    "gloss": "improve",
    "confidence": 0.95
  },
  {
    "hash": "d034bf1587321925",
    "word": "enrol",
    "pos": "verb",
    "cefr": "C1",
    "decision": "gloss",
    "gloss": "register",
    "confidence": 0.94
  },
  {
    "hash": "6abc1c232c816bcb",
    "word": "ensue",
    "pos": "verb",
    "cefr": "C1",
    "decision": "gloss",
    "gloss": "follow as result",
    "confidence": 0.92
  },
  {
    "hash": "2310accd9025794f",
    "word": "entertaining",
    "pos": "adjective",
    "cefr": "B2",
    "decision": "gloss",
    "gloss": "enjoyable",
    "confidence": 0.95
  }
]